kerspro/__init__.py
kerspro-0.0.5.dist-info/METADATA
kerspro-0.0.5.dist-info/WHEEL
kerspro-0.0.5.dist-info/top_level.txt
kerspro-0.0.5.dist-info/RECORD
