Metadata-Version: 2.1
Name: kerspro
Version: 0.0.5
Summary: package
Home-page: UNKNOWN
Author: nandan_6
Author-email: nandanpadia@gmail.com
License: UNKNOWN
Keywords: python
Platform: UNKNOWN
